{
  "Name": "D-latch",
  "NameLocation": 0,
  "ChipType": 0,
  "Size": {
    "x": 1.475,
    "y": 0.5
  },
  "Colour": {
    "r": 0.222467676,
    "g": 0.164044589,
    "b": 0.257037371,
    "a": 1
  },
  "InputPins":[
    {
      "Name":"Data",
      "ID":717375262,
      "Position":{
        "x":-4.25,
        "y":0.5
      },
      "BitCount":1,
      "Colour":0,
      "ValueDisplayMode":0
    },
    {
      "Name":"Write",
      "ID":1268803232,
      "Position":{
        "x":-3.0,
        "y":-0.375
      },
      "BitCount":1,
      "Colour":0,
      "ValueDisplayMode":0
    }
  ],
  "OutputPins":[
    {
      "Name":"OUT",
      "ID":2056436379,
      "Position":{
        "x":2.375,
        "y":-1.0
      },
      "BitCount":1,
      "Colour":0,
      "ValueDisplayMode":0
    }
  ],
  "SubChips":[
    {
      "Name":"NAND",
      "ID":2114152704,
      "Label":"",
      "Position":{
        "x":0.625,
        "y":0.25
      },
      "OutputPinColourInfo":[{"PinColour":0,"PinID":2}],
      "InternalData":null
    },
    {
      "Name":"NAND",
      "ID":464920506,
      "Label":"",
      "Position":{
        "x":0.625,
        "y":-1.0
      },
      "OutputPinColourInfo":[{"PinColour":0,"PinID":2}],
      "InternalData":null
    },
    {
      "Name":"NAND",
      "ID":1404829104,
      "Label":"",
      "Position":{
        "x":-0.875,
        "y":0.375
      },
      "OutputPinColourInfo":[{"PinColour":0,"PinID":2}],
      "InternalData":null
    },
    {
      "Name":"NAND",
      "ID":2001891057,
      "Label":"",
      "Position":{
        "x":-0.875,
        "y":-1.125
      },
      "OutputPinColourInfo":[{"PinColour":0,"PinID":2}],
      "InternalData":null
    },
    {
      "Name":"NAND",
      "ID":214572345,
      "Label":"",
      "Position":{
        "x":-2.375,
        "y":-1.25
      },
      "OutputPinColourInfo":[{"PinColour":0,"PinID":2}],
      "InternalData":null
    }
  ],
  "Wires":[
    {
      "SourcePinAddress":{
        "PinID":2,
        "PinOwnerID":2114152704
      },
      "TargetPinAddress":{
        "PinID":0,
        "PinOwnerID":464920506
      },
      "ConnectionType":0,
      "ConnectedWireIndex":-1,
      "ConnectedWireSegmentIndex":-1,
      "Points":[{"x":0.0,"y":0.0},{"x":1.375,"y":0.25},{"x":1.375,"y":-0.125},{"x":-0.125,"y":-0.625},{"x":-0.125,"y":-0.875},{"x":0.0,"y":0.0}]
    },
    {
      "SourcePinAddress":{
        "PinID":2,
        "PinOwnerID":464920506
      },
      "TargetPinAddress":{
        "PinID":1,
        "PinOwnerID":2114152704
      },
      "ConnectionType":0,
      "ConnectedWireIndex":-1,
      "ConnectedWireSegmentIndex":-1,
      "Points":[{"x":0.0,"y":0.0},{"x":1.375,"y":-1.0},{"x":1.375,"y":-0.75},{"x":-0.125,"y":-0.125},{"x":-0.125,"y":0.125},{"x":0.0,"y":0.0}]
    },
    {
      "SourcePinAddress":{
        "PinID":0,
        "PinOwnerID":717375262
      },
      "TargetPinAddress":{
        "PinID":0,
        "PinOwnerID":1404829104
      },
      "ConnectionType":0,
      "ConnectedWireIndex":-1,
      "ConnectedWireSegmentIndex":-1,
      "Points":[{"x":0.0,"y":0.0},{"x":0.0,"y":0.0}]
    },
    {
      "SourcePinAddress":{
        "PinID":2,
        "PinOwnerID":214572345
      },
      "TargetPinAddress":{
        "PinID":1,
        "PinOwnerID":2001891057
      },
      "ConnectionType":0,
      "ConnectedWireIndex":-1,
      "ConnectedWireSegmentIndex":-1,
      "Points":[{"x":0.0,"y":0.0},{"x":0.0,"y":0.0}]
    },
    {
      "SourcePinAddress":{
        "PinID":0,
        "PinOwnerID":717375262
      },
      "TargetPinAddress":{
        "PinID":0,
        "PinOwnerID":214572345
      },
      "ConnectionType":1,
      "ConnectedWireIndex":2,
      "ConnectedWireSegmentIndex":0,
      "Points":[{"x":-3.25,"y":0.5},{"x":-3.25,"y":-1.125},{"x":0.0,"y":0.0}]
    },
    {
      "SourcePinAddress":{
        "PinID":0,
        "PinOwnerID":717375262
      },
      "TargetPinAddress":{
        "PinID":1,
        "PinOwnerID":214572345
      },
      "ConnectionType":1,
      "ConnectedWireIndex":4,
      "ConnectedWireSegmentIndex":0,
      "Points":[{"x":-3.25,"y":-1.125},{"x":-3.25,"y":-1.375},{"x":0.0,"y":0.0}]
    },
    {
      "SourcePinAddress":{
        "PinID":2,
        "PinOwnerID":2001891057
      },
      "TargetPinAddress":{
        "PinID":1,
        "PinOwnerID":464920506
      },
      "ConnectionType":0,
      "ConnectedWireIndex":-1,
      "ConnectedWireSegmentIndex":-1,
      "Points":[{"x":0.0,"y":0.0},{"x":0.0,"y":0.0}]
    },
    {
      "SourcePinAddress":{
        "PinID":2,
        "PinOwnerID":1404829104
      },
      "TargetPinAddress":{
        "PinID":0,
        "PinOwnerID":2114152704
      },
      "ConnectionType":0,
      "ConnectedWireIndex":-1,
      "ConnectedWireSegmentIndex":-1,
      "Points":[{"x":0.0,"y":0.0},{"x":0.0,"y":0.0}]
    },
    {
      "SourcePinAddress":{
        "PinID":2,
        "PinOwnerID":464920506
      },
      "TargetPinAddress":{
        "PinID":0,
        "PinOwnerID":2056436379
      },
      "ConnectionType":1,
      "ConnectedWireIndex":1,
      "ConnectedWireSegmentIndex":0,
      "Points":[{"x":1.375,"y":-1.0},{"x":0.0,"y":0.0}]
    },
    {
      "SourcePinAddress":{
        "PinID":0,
        "PinOwnerID":1268803232
      },
      "TargetPinAddress":{
        "PinID":1,
        "PinOwnerID":1404829104
      },
      "ConnectionType":0,
      "ConnectedWireIndex":-1,
      "ConnectedWireSegmentIndex":-1,
      "Points":[{"x":0.0,"y":0.0},{"x":-1.625,"y":-0.375},{"x":-1.625,"y":0.25},{"x":0.0,"y":0.0}]
    },
    {
      "SourcePinAddress":{
        "PinID":0,
        "PinOwnerID":1268803232
      },
      "TargetPinAddress":{
        "PinID":0,
        "PinOwnerID":2001891057
      },
      "ConnectionType":1,
      "ConnectedWireIndex":9,
      "ConnectedWireSegmentIndex":0,
      "Points":[{"x":-1.625,"y":-0.375},{"x":-1.625,"y":-1.0},{"x":0.0,"y":0.0}]
    }
  ],
  "Displays": null
}